[
    {
        "value": 100,
        "name": "Inhalte und Werkzeuge",
        "path": "Inhalte und Werkzeuge",
        "children": [
            {
                "value": 20,
                "name": "Technische Standards",
                "id": "1-1",
                "path": "Inhalte und Werkzeuge/Technische Standards"
            },
            {
                "value": 20,
                "name": "Rechtliche Standards",
                "id": "1-2",
                "path": "Inhalte und Werkzeuge/Rechtliche Standards"
            },
            {
                "value": 20,
                "name": "Prüfverfahren",
                "id": "1-3",
                "path": "Inhalte und Werkzeuge/Prüfverfahren"
            },
            {
                "value": 20,
                "name": "OER",
                "id": "1-4",
                "path": "Inhalte und Werkzeuge/OER"
            },
            {
                "value": 20,
                "name": "Metadaten",
                "path": "Inhalte und Werkzeuge/Metadaten"
            },
            {
                "value": 20,
                "name": "Repositorien / Referatorien",
                "path": "Inhalte und Werkzeuge/Repositorien / Referatorien"
            },
            {
                "value": 20,
                "name": "Schnittstellen",
                "path": "Inhalte und Werkzeuge/Schnittstellen"
            },
            {
                "value": 20,
                "name": "Learning Record Store",
                "path": "Inhalte und Werkzeuge/Learning Record Store"
            },
            {
                "value": 20,
                "name": "Office-Anwendungen",
                "path": "Inhalte und Werkzeuge/Office-Anwendungen"
            },
            {
                "value": 20,
                "name": "Lern-Management-System (LMS)",
                "path": "Inhalte und Werkzeuge/Lern-Management-System (LMS)"
            },
            {
                "value": 20,
                "name": "Weitere Tools",
                "path": "Inhalte und Werkzeuge/Weitere Tools",
                "children": [
                    {
                        "value": 20,
                        "name": "Digitale Schulbücher",
                        "path": "Inhalte und Werkzeuge/Weitere Tools/Digitale Schulbücher"
                    },
                    {
                        "value": 20,
                        "name": "Lehrmittel Portale",
                        "path": "Inhalte und Werkzeuge/Weitere Tools/Lehrmittel Portale"
                    }
                ]
            }
        ]
    },
    {
        "value": 100,
        "name": "Pädagogische Oberfläche",
        "path": "Pädagogische Oberfläche",
        "children": [
            {
                "value": 20,
                "name": "Dateiablage",
                "path": "Inhalte und Werkzeuge/Dateiablage"
            },
            {
                "value": 20,
                "name": "Gemeinsame Dokumentenbearbeitung",
                "path": "Inhalte und Werkzeuge/Gemeinsame Dokumentenbearbeitung"
            },
            {
                "value": 20,
                "name": "Lern- und Projektgruppen einrichten und verwalten",
                "path": "Inhalte und Werkzeuge/Lern- und Projektgruppen einrichten und verwalten"
            },
            {
                "value": 20,
                "name": "Wissensmanagement",
                "path": "Inhalte und Werkzeuge/Wissensmanagement"
            },
            {
                "value": 20,
                "name": "Mail, Kalender",
                "path": "Inhalte und Werkzeuge/Mail, Kalender"
            },
            {
                "value": 20,
                "name": "Chat",
                "path": "Inhalte und Werkzeuge/Chat"
            },
            {
                "value": 20,
                "name": "Videokonferenzen",
                "path": "Inhalte und Werkzeuge/Videokonferenzen"
            }
        ]
    },
    {
        "value": 100,
        "name": "Hardware",
        "path": "Hardware",
        "children": [
            {
                "value": 20,
                "name": "Stationäre Arbeitsplätze",
                "path": "Inhalte und Werkzeuge/Stationäre Arbeitsplätze"
            },
            {
                "value": 20,
                "name": "Netzwerkinfrastruktur",
                "path": "Inhalte und Werkzeuge/Netzwerkinfrastruktur"
            },
            {
                "value": 20,
                "name": "Lern- und Projektgruppen einrichten und verwalten",
                "path": "Inhalte und Werkzeuge/Lern- und Projektgruppen einrichten und verwalten"
            },
            {
                "value": 20,
                "name": "Wissensmanagement",
                "path": "Inhalte und Werkzeuge/Wissensmanagement"
            },
            {
                "value": 20,
                "name": "Mail, Kalender",
                "path": "Inhalte und Werkzeuge/Mail, Kalender"
            },
            {
                "value": 20,
                "name": "Chat",
                "path": "Inhalte und Werkzeuge/Chat"
            },
            {
                "value": 20,
                "name": "Videokonferenzen",
                "path": "Inhalte und Werkzeuge/Videokonferenzen"
            }
        ]
    }
]
